riptide_proxy/__init__.py
riptide_proxy/__main__.py
riptide_proxy/abstract_plugin.py
riptide_proxy/autostart_restrict.py
riptide_proxy/privileges.py
riptide_proxy/profiling.py
riptide_proxy/project_loader.py
riptide_proxy/resources.py
riptide_proxy/ssl_key.py
riptide_proxy/server/__init__.py
riptide_proxy/server/http.py
riptide_proxy/server/starter.py
riptide_proxy/server/websocket/__init__.py
riptide_proxy/server/websocket/autostart.py
riptide_proxy/server/websocket/others.py
riptide_proxy/tpl/back_to_front.html
riptide_proxy/tpl/foot.html
riptide_proxy/tpl/head.html
riptide_proxy/tpl/pp_500.html
riptide_proxy/tpl/pp_500_project_load.html
riptide_proxy/tpl/pp_502.html
riptide_proxy/tpl/pp_gateway_timeout.html
riptide_proxy/tpl/pp_landing_page.html
riptide_proxy/tpl/pp_no_main_service.html
riptide_proxy/tpl/pp_project_not_found.html
riptide_proxy/tpl/pp_project_not_started.html
riptide_proxy/tpl/pp_service_not_found.html
riptide_proxy/tpl/pp_start_project.html
riptide_proxy/tpl/project_list.html
riptide_proxy/tpl/service_list.html
riptide_proxy/tpl/socket.js
riptide_proxy/tpl/styles.css
riptide_proxy-0.9.1.dist-info/LICENSE
riptide_proxy-0.9.1.dist-info/METADATA
riptide_proxy-0.9.1.dist-info/WHEEL
riptide_proxy-0.9.1.dist-info/entry_points.txt
riptide_proxy-0.9.1.dist-info/top_level.txt
riptide_proxy-0.9.1.dist-info/RECORD
