Metadata-Version: 2.1
Name: riptide-proxy
Version: 0.9.1
Summary: Tool to manage development environments for web applications using containers - HTTP and WebSocket Reverse Proxy Server
Author-email: Marco Köpcke <hello@capypara.de>
License: MIT License
Project-URL: Repository, https://github.com/theCapypara/riptide-proxy
Project-URL: Documentation, https://riptide-docs.readthedocs.io
Classifier: Development Status :: 4 - Beta
Classifier: Programming Language :: Python
Classifier: Intended Audience :: Developers
Classifier: License :: OSI Approved :: MIT License
Classifier: Programming Language :: Python :: 3.8
Classifier: Programming Language :: Python :: 3.9
Classifier: Programming Language :: Python :: 3.10
Classifier: Programming Language :: Python :: 3.11
Classifier: Programming Language :: Python :: 3.12
Classifier: Programming Language :: Python :: 3.13
Requires-Python: >=3.8
License-File: LICENSE
Requires-Dist: riptide-lib <0.10,>=0.9
Requires-Dist: tornado >=6.0
Requires-Dist: Click >=7.0
Requires-Dist: certauth >=1.3
Requires-Dist: python-prctl >=1.7 ; sys_platform == "linux"
Provides-Extra: profiling
Requires-Dist: guppy3 >=3.0.9 ; extra == 'profiling'
